zano/__init__.py
zano/bundle.py
zano/commands.py
zano/env.py
zano/errors.py
zano/fs_nodes.py
zano/fs_tools.py
zano/shared.py
zano/tasks.py
zano-0.6.0.dist-info/METADATA
zano-0.6.0.dist-info/WHEEL
zano-0.6.0.dist-info/entry_points.txt
zano-0.6.0.dist-info/RECORD
