Metadata-Version: 2.3
Name: zano
Version: 0.6.0
Summary: Zano is a CLI bidirectional synchronizer for Linux.
Author: Nicolas Hainaux
Author-email: nh.techn@gmail.com
Requires-Python: >=3.11,<4.0
Classifier: Programming Language :: Python :: 3
Classifier: Programming Language :: Python :: 3.11
Classifier: Programming Language :: Python :: 3.12
Classifier: Programming Language :: Python :: 3.13
Requires-Dist: Send2Trash (>=1.8.0,<2.0.0)
Requires-Dist: click (>=8.0.1,<9.0.0)
Requires-Dist: microlib (>=1.10.4,<2.0.0)
Requires-Dist: toml (>=0.10.2,<0.11.0)
Requires-Dist: tqdm (>=4.62.3,<5.0.0)
